AUTHORS.rst
CONTRIBUTING.rst
HISTORY.rst
LICENSE
MANIFEST.in
README.rst
setup.cfg
setup.py
docs/Makefile
docs/authors.rst
docs/conf.py
docs/contributing.rst
docs/history.rst
docs/index.rst
docs/installation.rst
docs/make.bat
docs/readme.rst
docs/usage.rst
msg91/__init__.py
msg91/msg91.py
msg91_client.egg-info/PKG-INFO
msg91_client.egg-info/SOURCES.txt
msg91_client.egg-info/dependency_links.txt
msg91_client.egg-info/not-zip-safe
msg91_client.egg-info/pbr.json
msg91_client.egg-info/requires.txt
msg91_client.egg-info/top_level.txt
tests/__init__.py
tests/test_msg91.py