Metadata-Version: 1.1
Name: msg91-client
Version: 0.4.1
Summary: A simple python client for MSG91 APIs
Home-page: https://github.com/suraj-arya/msg91
Author: Suraj Arya
Author-email: suraj.p.arya@gmail.com
License: ISCL
Keywords: msg91
Platform: UNKNOWN
Classifier: Development Status :: 2 - Pre-Alpha
Classifier: Intended Audience :: Developers
Classifier: License :: OSI Approved :: ISC License (ISCL)
Classifier: Natural Language :: English
Classifier: Programming Language :: Python :: 2
Classifier: Programming Language :: Python :: 2.6
Classifier: Programming Language :: Python :: 2.7
Classifier: Programming Language :: Python :: 3
Classifier: Programming Language :: Python :: 3.3
Classifier: Programming Language :: Python :: 3.4
Classifier: Programming Language :: Python :: 3.5
